setup.py
PyWaves.egg-info/PKG-INFO
PyWaves.egg-info/SOURCES.txt
PyWaves.egg-info/dependency_links.txt
PyWaves.egg-info/requires.txt
PyWaves.egg-info/top_level.txt
pywaves/ParallelPyWaves.py
pywaves/WXFeeCalculator.py
pywaves/__init__.py
pywaves/address.py
pywaves/asset.py
pywaves/contract.py
pywaves/crypto.py
pywaves/oracle.py
pywaves/order.py
pywaves/txGenerator.py
pywaves/txSigner.py
pywaves/protobuf/waves/amount_pb2.py
pywaves/protobuf/waves/block_pb2.py
pywaves/protobuf/waves/invoke_script_result_pb2.py
pywaves/protobuf/waves/order_pb2.py
pywaves/protobuf/waves/recipient_pb2.py
pywaves/protobuf/waves/transaction_pb2.py