Metadata-Version: 1.0
Name: PyWaves
Version: 1.0.1
Summary: Object-oriented library for the Waves blockchain platform
Home-page: http://github.com/pywaves/pywaves
Author: PyWaves Developers
Author-email: dev@pywaves.org
License: MIT
Keywords: waves,blockchain,analytics
Platform: UNKNOWN
